odoo8_addon_mrp_repair_discount-8.0.1.0.0.99.dev12-py3.8-nspkg.pth
odoo_addons/mrp_repair_discount/README.rst
odoo_addons/mrp_repair_discount/__init__.py
odoo_addons/mrp_repair_discount/__openerp__.py
odoo_addons/mrp_repair_discount/i18n/ca.po
odoo_addons/mrp_repair_discount/i18n/de.po
odoo_addons/mrp_repair_discount/i18n/el_GR.po
odoo_addons/mrp_repair_discount/i18n/es.po
odoo_addons/mrp_repair_discount/i18n/es_ES.po
odoo_addons/mrp_repair_discount/i18n/fi.po
odoo_addons/mrp_repair_discount/i18n/fr.po
odoo_addons/mrp_repair_discount/i18n/gl.po
odoo_addons/mrp_repair_discount/i18n/hr_HR.po
odoo_addons/mrp_repair_discount/i18n/it.po
odoo_addons/mrp_repair_discount/i18n/mrp_repair_discount.pot
odoo_addons/mrp_repair_discount/i18n/pt_BR.po
odoo_addons/mrp_repair_discount/i18n/pt_PT.po
odoo_addons/mrp_repair_discount/i18n/ro.po
odoo_addons/mrp_repair_discount/i18n/ru.po
odoo_addons/mrp_repair_discount/i18n/sl.po
odoo_addons/mrp_repair_discount/i18n/tr.po
odoo_addons/mrp_repair_discount/i18n/tr_TR.po
odoo_addons/mrp_repair_discount/i18n/zh_CN.po
odoo_addons/mrp_repair_discount/models/__init__.py
odoo_addons/mrp_repair_discount/models/mrp_repair.py
odoo_addons/mrp_repair_discount/static/description/icon.png
odoo_addons/mrp_repair_discount/test/mrp_repair_discount.yml
odoo_addons/mrp_repair_discount/tests/__init__.py
odoo_addons/mrp_repair_discount/tests/test_mrp_repair_discount.py
odoo_addons/mrp_repair_discount/views/mrp_repair_view.xml
odoo8_addon_mrp_repair_discount-8.0.1.0.0.99.dev12.dist-info/METADATA
odoo8_addon_mrp_repair_discount-8.0.1.0.0.99.dev12.dist-info/WHEEL
odoo8_addon_mrp_repair_discount-8.0.1.0.0.99.dev12.dist-info/namespace_packages.txt
odoo8_addon_mrp_repair_discount-8.0.1.0.0.99.dev12.dist-info/top_level.txt
odoo8_addon_mrp_repair_discount-8.0.1.0.0.99.dev12.dist-info/RECORD
